libname/__init__.py
libname/nqueen.py
upe-0.0.8.dist-info/METADATA
upe-0.0.8.dist-info/WHEEL
upe-0.0.8.dist-info/top_level.txt
upe-0.0.8.dist-info/RECORD
